traVer
